<annotation>
	<folder>train</folder>
	<filename>28.jpg</filename>
	<path>C:\Users\Minion\Desktop\images\train\28.jpg</path>
	<source>
		<database>Unknown</database>
	</source>
	<size>
		<width>800</width>
		<height>600</height>
		<depth>3</depth>
	</size>
	<segmented>0</segmented>
	<object>
		<name>SIM800</name>
		<pose>Unspecified</pose>
		<truncated>0</truncated>
		<difficult>0</difficult>
		<bndbox>
			<xmin>155</xmin>
			<ymin>322</ymin>
			<xmax>326</xmax>
			<ymax>491</ymax>
		</bndbox>
	</object>
	<object>
		<name>Arduino Mega 2560</name>
		<pose>Unspecified</pose>
		<truncated>1</truncated>
		<difficult>0</difficult>
		<bndbox>
			<xmin>400</xmin>
			<ymin>361</ymin>
			<xmax>691</xmax>
			<ymax>600</ymax>
		</bndbox>
	</object>
	<object>
		<name>Arduino UNO</name>
		<pose>Unspecified</pose>
		<truncated>0</truncated>
		<difficult>0</difficult>
		<bndbox>
			<xmin>60</xmin>
			<ymin>122</ymin>
			<xmax>263</xmax>
			<ymax>317</ymax>
		</bndbox>
	</object>
	<object>
		<name>HC-05</name>
		<pose>Unspecified</pose>
		<truncated>0</truncated>
		<difficult>0</difficult>
		<bndbox>
			<xmin>278</xmin>
			<ymin>185</ymin>
			<xmax>375</xmax>
			<ymax>263</ymax>
		</bndbox>
	</object>
	<object>
		<name>Sonar Sensor</name>
		<pose>Unspecified</pose>
		<truncated>0</truncated>
		<difficult>0</difficult>
		<bndbox>
			<xmin>394</xmin>
			<ymin>245</ymin>
			<xmax>520</xmax>
			<ymax>305</ymax>
		</bndbox>
	</object>
	<object>
		<name>Arduino Pro Mini</name>
		<pose>Unspecified</pose>
		<truncated>0</truncated>
		<difficult>0</difficult>
		<bndbox>
			<xmin>421</xmin>
			<ymin>83</ymin>
			<xmax>507</xmax>
			<ymax>143</ymax>
		</bndbox>
	</object>
	<object>
		<name>NodeMCU</name>
		<pose>Unspecified</pose>
		<truncated>0</truncated>
		<difficult>0</difficult>
		<bndbox>
			<xmin>538</xmin>
			<ymin>146</ymin>
			<xmax>692</xmax>
			<ymax>262</ymax>
		</bndbox>
	</object>
</annotation>
